{
  "businessUnit": "swi",
  "container": 10,
  "comScoreVirtualSite": "swi-player-ios-v",
  "netMetrixIdentifier": "srgplayer",
  "voiceOverLanguageCode": "en",
  "googleCastReceiverIdentifier": "1AC2931D",
  "appStoreProductIdentifier": 920785201,
  "playURL": "https://play.swissinfo.ch/play/",
  "middlewareURL": "https://playfff.herokuapp.com",
  "feedbackURL": "https://play.typeform.com/to/bR8TQq",
  "searchOptions": "videos",
  "videoSections": "tvTrending,tvFavoriteShows,tvTopics",
  "tvTrendingEpisodesOnly": true,
  "tvTrendingEditorialLimit": 2,
  "tvFeaturedHomeSectionHeaderHidden": true,
  "topicSections": "latest,mostPopular",
  "topicSectionsWithSubtopics": "latest",
  "minimumSocialViewCount": 50,
  "dataProtectionURL": "https://www.swissinfo.ch/eng/data-privacy-statement/133174",
  "whatsNewURL": "https://pastebin.com/raw/BRC1hPbt",
  "downloadsHintsHidden": true,
  "moreEpisodesHidden": true,
  "moduleDefaultLinkColor": "#D2D2D2",
  "moduleDefaultTextColor": "#969696",
  "continuousPlaybackPlayerViewTransitionDuration": 5,
  "continuousPlaybackForegroundTransitionDuration": 0,
  "continuousPlaybackBackgroundTransitionDuration": 0,
  "endTolerance": 10,
  "endToleranceRatio": 0.01,
  "searchSettingsHidden": true,
  "showsSearchHidden": true,
  "hiddenOnboardings": "account,favorites_account,resume_playback_account,watch_later_account",
  "searchSettingSubtitledHidden": true,
  "subtitleAvailabilityHidden": true,
  "audioDescriptionAvailabilityHidden": true
}
